{"P2": {"labels": ["\u8bd7\u6b4c"], "postTitle": "\u542c\u96e8\u9504\u82b1", "postUrl": "post/ting-yu-chu-hua.html", "createdDate": "2024-07-23", "dateLabelColor": "#bc4c00"}, "P1": {"labels": ["\u8bd7\u6b4c"], "postTitle": "\u53e4\u8bd7\u300a\u7f05\u6000\u300b", "postUrl": "post/gu-shi-%E3%80%8A-mian-huai-%E3%80%8B.html", "createdDate": "2024-07-23", "dateLabelColor": "#bc4c00"}, "labelColorDict": {"bug": "#d73a4a", "documentation": "#0075ca", "duplicate": "#cfd3d7", "enhancement": "#a2eeef", "good first issue": "#7057ff", "help wanted": "#008672", "invalid": "#e4e669", "question": "#d876e3", "wontfix": "#ffffff", "\u8bd7\u6b4c": "#0e8a16"}}